<?xml version="1.0" encoding="UTF-8"?>
<conferences><conference id="120"><titreFr>1</titreFr><titreEn>2</titreEn><resumeFr>&lt;u&gt;Bonjour&lt;/u&gt;, &lt;b&gt;baguette &lt;/b&gt;! &lt;i&gt;Baguette &lt;/i&gt;! </resumeFr><resumeEn>&lt;div align="center"&gt;Hello, I like &lt;font face="comic sans ms"&gt;tea &lt;/font&gt;and &lt;font size="4"&gt;umbrellas &lt;/font&gt;!&lt;br&gt;&lt;/div&gt;</resumeEn><localisation>Truc</localisation><intervenant>Bidule</intervenant><datetime>2000-10-10T22:20:00+00:00</datetime></conference><conference id="12"><titreFr>Gestion des grands projets</titreFr><titreEn>Big Project Management</titreEn><resumeFr/><resumeEn>First, you will need to be patient</resumeEn><localisation>Paris</localisation><intervenant>SAID EL FARKH</intervenant><datetime>2016-07-14T02:45:00+02:00</datetime></conference><conference id="4"><titreFr>Les effets de la cigarettes</titreFr><titreEn>the effects of the cigarettes</titreEn><resumeFr>Bla bla bla</resumeFr><resumeEn/><localisation>Clermont-Ferrand</localisation><intervenant>Pierre DUPUIS</intervenant><datetime>2018-01-05T17:30:00+00:00</datetime></conference><conference id="5"><titreFr>Le terrorisme</titreFr><titreEn>The Terrorism</titreEn><resumeFr>Bla bla bla</resumeFr><resumeEn/><localisation>Paris</localisation><intervenant>Said EL FARKH</intervenant><datetime>2018-01-05T20:00:00+00:00</datetime></conference><conference id="6"><titreFr>Effet de serre</titreFr><titreEn>Global Warming</titreEn><resumeFr>Bla bla bla</resumeFr><resumeEn/><localisation>paris</localisation><intervenant>said El farkh</intervenant><datetime>2018-01-05T21:00:00+00:00</datetime></conference><conference id="10"><titreFr>Comment conquérir la terre?</titreFr><titreEn>How to conquer Earth?</titreEn><resumeFr>Ou pourquoi il ne faut pas envoyer des gens le faire à sa place.</resumeFr><resumeEn>Or why you will have to get off your chair and do things by yourself</resumeEn><localisation>Earth</localisation><intervenant>Thanos</intervenant><datetime>2018-04-25T08:00:00+00:00</datetime></conference><conference id="8"><titreFr>Le financement des campagnes politiques</titreFr><titreEn>financing of political campaigns</titreEn><resumeFr>Bla bla bla</resumeFr><resumeEn/><localisation>Maison d'arrêt de la Santé</localisation><intervenant>Nicolas Sarkozy</intervenant><datetime>2023-10-19T13:00:00+00:00</datetime></conference></conferences>
